newpychromedriver/__init__.py
newpychromedriver/chromedriver-linux64/LICENSE.chromedriver
newpychromedriver/chromedriver-linux64/chromedriver
newpychromedriver/chromedriver-mac-arm64/LICENSE.chromedriver
newpychromedriver/chromedriver-mac-arm64/chromedriver
newpychromedriver/chromedriver-mac-x64/LICENSE.chromedriver
newpychromedriver/chromedriver-mac-x64/chromedriver
newpychromedriver/chromedriver-win32/LICENSE.chromedriver
newpychromedriver/chromedriver-win32/chromedriver.exe
newpychromedriver/chromedriver-win64/LICENSE.chromedriver
newpychromedriver/chromedriver-win64/chromedriver.exe
newpychromedriver-115.0.5790.170.dist-info/LICENSE
newpychromedriver-115.0.5790.170.dist-info/METADATA
newpychromedriver-115.0.5790.170.dist-info/WHEEL
newpychromedriver-115.0.5790.170.dist-info/top_level.txt
newpychromedriver-115.0.5790.170.dist-info/RECORD
