Metadata-Version: 2.1
Name: newpychromedriver
Version: 115.0.5790.170
Summary: A package to sync chrome driver to lastest version
Home-page: UNKNOWN
Author: biao.li
Author-email: biao.li@flexiv.com
License: UNKNOWN
Keywords: chromedriver chrome driver
Platform: UNKNOWN
Classifier: Programming Language :: Python :: 3
Classifier: License :: OSI Approved :: Apache Software License
Classifier: Operating System :: OS Independent
